kokushibyo/__init__.py
kokushibyo/main.py
kokushibyo/utils.py
kokushibyo-0.6.66.dist-info/METADATA
kokushibyo-0.6.66.dist-info/WHEEL
kokushibyo-0.6.66.dist-info/top_level.txt
kokushibyo-0.6.66.dist-info/RECORD
