Metadata-Version: 2.1
Name: kokushibyo
Version: 0.6.66
Summary: Filesystem handling utilities
Author-email: "Julian M. Kleber" <julian.m.kleber@gmail.com>
Project-URL: Homepage, https://www.codeberg.org/cap_jmk/kokushibyo.git
Project-URL: Bug Tracker, https://www.codeberg.org/cap_jmk/kokushibyo.git/issues
Classifier: Programming Language :: Python :: 3
Classifier: License :: OSI Approved :: GNU General Public License v3 (GPLv3)
Classifier: Operating System :: OS Independent
Requires-Python: >=3.8
Requires-Dist: sailing-log
